{  "nodes": [
     {"id":"1", "fontcolor":"blue","shape":"plaintext","label":"Cluster ID: 74\nSpecific Mutation Type: Response time change\nCost: 6039\nOverall Mutation Type: Response_Time_Change\nCandidate originating clusters: \n\nAvg. response times: 3483 us ; 3650 us\nStandard Deviations: 47 us ; 108 us\nKS-Test2 P-value: 0.000\nCluster likelihood: 0.0005 ; 0.0004\nPercent makeup: 58 / 42\nrequests: 36 ; 26"}
    ,{"id":"10245225243073327.10245225243205178", "label":"e10__t3__RPC_REPLY_TYPE\nDEFAULT"}
    ,{"id":"10245225243073327.10245225243233243", "label":"e10__t3__MDS_SETATTR_REPLY_TYPE\nDEFAULT"}
    ,{"id":"10245225243073327.10245225243265388", "label":"e10__t3__NFS3_CREATE_REPLY_TYPE\nDEFAULT"}
    ,{"id":"10245225242891722.10245225242903265", "label":"e4__t3__SSIO_END_TYPE\nSSIO_WRITE_END"}
    ,{"id":"10245225242891722.10245225242964885", "label":"e4__t3__MDS_LOCK_RELEASE_TYPE\nDEFAULT"}
    ,{"id":"10245225242891722.10245225243051225", "label":"e4__t3__RPC_SERVER_REPLY_SENT_TYPE\nDEFAULT"}
    ,{"id":"10245264206126378.10245225242876775", "label":"e4__t3__RPC_REPLY_TYPE\nDEFAULT"}
    ,{"id":"10245225241306425.10245264206055510", "label":"e255__t3__FRONTEND_WRITE_CALL_TYPE\nDEFAULT"}
    ,{"id":"10245225241306425.10245264206073773", "label":"e255__t3__FRONTEND_BLOCK_OP_START_TYPE\nFRONTEND_WRITE"}
    ,{"id":"10245225241306425.10245264206120310", "label":"e255__t3__FRONTEND_WRITE_REPLY_TYPE\nDEFAULT"}
    ,{"id":"10245225241279140.10245225241301768", "label":"e4__t3__RPC_CALL_TYPE\nDEFAULT"}
    ,{"id":"10245225240539850.10245225240695820", "label":"e4__t3__RPC_SERVER_CALL_RECEIVED_TYPE\nDEFAULT"}
    ,{"id":"10245225240539850.10245225240847350", "label":"e4__t3__MDS_LOCK_ACQUIRE_TYPE\nDEFAULT"}
    ,{"id":"10245225240539850.10245225240942720", "label":"e4__t3__MDS_LOCK_DB_ACQUIRE_TYPE\nDEFAULT"}
    ,{"id":"10245225240539850.10245225240977468", "label":"e4__t3__MDS_LOCK_DB_RELEASE_TYPE\nDEFAULT"}
    ,{"id":"10245225240539850.10245225241114020", "label":"e4__t3__MDS_LOOKUP_CALL_TYPE\nDEFAULT"}
    ,{"id":"10245225240539850.10245225241136663", "label":"e4__t3__MDS_LOCK_ACQUIRE_TYPE\nDEFAULT"}
    ,{"id":"10245225240539850.10245225241162703", "label":"e4__t3__MDS_LOCK_RELEASE_TYPE\nDEFAULT"}
    ,{"id":"10245225240539850.10245225241174020", "label":"e4__t3__MDS_LOOKUP_REPLY_TYPE\nMDSCLIENTCACHE_HIT"}
    ,{"id":"10245225240539850.10245225241183358", "label":"e4__t3__SSIO_START_TYPE\nSSIO_WRITE_START"}
    ,{"id":"10245225240539850.10245225241197008", "label":"e4__t3__ENCODE_START_TYPE\nDEFAULT"}
    ,{"id":"10245225240539850.10245225241270155", "label":"e4__t3__ENCODE_END_TYPE\nDEFAULT"}
    ,{"id":"10245225240279840.10245225240292867", "label":"e10__t3__SSIO_END_TYPE\nSSIO_WRITE_END"}
    ,{"id":"10245225240279840.10245225240316215", "label":"e10__t3__MDS_SETATTR_CALL_TYPE\nDEFAULT"}
    ,{"id":"10245225240279840.10245225240534165", "label":"e10__t3__RPC_CALL_TYPE\nDEFAULT"}
    ,{"id":"10245212653272938.10245225240261405", "label":"e10__t3__RPC_REPLY_TYPE\nDEFAULT"}
    ,{"id":"10245225239077703.10245212653147680", "label":"e100__t3__FRONTEND_WRITE_CALL_TYPE\nDEFAULT"}
    ,{"id":"10245225239077703.10245212653168125", "label":"e100__t3__FRONTEND_BLOCK_OP_START_TYPE\nFRONTEND_WRITE"}
    ,{"id":"10245225239077703.10245212653266368", "label":"e100__t3__FRONTEND_WRITE_REPLY_TYPE\nDEFAULT"}
    ,{"id":"10245225239050590.10245225239072790", "label":"e10__t3__RPC_CALL_TYPE\nDEFAULT"}
    ,{"id":"10245225238542540.10245225238656953", "label":"e10__t3__RPC_REPLY_TYPE\nDEFAULT"}
    ,{"id":"10245225238542540.10245225238706565", "label":"e10__t3__MDS_SETATTR_REPLY_TYPE\nDEFAULT"}
    ,{"id":"10245225238542540.10245225238900538", "label":"e10__t3__NFS_CACHE_BLOCK_OP_TYPE\nNFSCACHE_EVICT"}
    ,{"id":"10245225238542540.10245225238920705", "label":"e10__t3__MDS_LOOKUP_CALL_TYPE\nDEFAULT"}
    ,{"id":"10245225238542540.10245225238942913", "label":"e10__t3__MDS_LOOKUP_REPLY_TYPE\nMDSCLIENTCACHE_HIT"}
    ,{"id":"10245225238542540.10245225238956053", "label":"e10__t3__SSIO_START_TYPE\nSSIO_WRITE_START"}
    ,{"id":"10245225238542540.10245225238976183", "label":"e10__t3__ENCODE_START_TYPE\nDEFAULT"}
    ,{"id":"10245225238542540.10245225239036985", "label":"e10__t3__ENCODE_END_TYPE\nDEFAULT"}
    ,{"id":"10245225238383810.10245225238393230", "label":"e4__t3__SSIO_END_TYPE\nSSIO_WRITE_END"}
    ,{"id":"10245225238383810.10245225238451880", "label":"e4__t3__MDS_LOCK_RELEASE_TYPE\nDEFAULT"}
    ,{"id":"10245225238383810.10245225238537950", "label":"e4__t3__RPC_SERVER_REPLY_SENT_TYPE\nDEFAULT"}
    ,{"id":"10245264201668153.10245225238371360", "label":"e4__t3__RPC_REPLY_TYPE\nDEFAULT"}
    ,{"id":"10245225236922457.10245264201597240", "label":"e255__t3__FRONTEND_WRITE_CALL_TYPE\nDEFAULT"}
    ,{"id":"10245225236922457.10245264201615758", "label":"e255__t3__FRONTEND_BLOCK_OP_START_TYPE\nFRONTEND_WRITE"}
    ,{"id":"10245225236922457.10245264201662093", "label":"e255__t3__FRONTEND_WRITE_REPLY_TYPE\nDEFAULT"}
    ,{"id":"10245225236900542.10245225236917822", "label":"e4__t3__RPC_CALL_TYPE\nDEFAULT"}
    ,{"id":"10245225236233613.10245225236391982", "label":"e4__t3__RPC_SERVER_CALL_RECEIVED_TYPE\nDEFAULT"}
    ,{"id":"10245225236233613.10245225236536635", "label":"e4__t3__MDS_LOCK_ACQUIRE_TYPE\nDEFAULT"}
    ,{"id":"10245225236233613.10245225236624317", "label":"e4__t3__MDS_LOCK_DB_ACQUIRE_TYPE\nDEFAULT"}
    ,{"id":"10245225236233613.10245225236653800", "label":"e4__t3__MDS_LOCK_DB_RELEASE_TYPE\nDEFAULT"}
    ,{"id":"10245225236233613.10245225236762220", "label":"e4__t3__MDS_LOOKUP_CALL_TYPE\nDEFAULT"}
    ,{"id":"10245225236233613.10245225236783175", "label":"e4__t3__MDS_LOCK_ACQUIRE_TYPE\nDEFAULT"}
    ,{"id":"10245225236233613.10245225236806620", "label":"e4__t3__MDS_LOCK_RELEASE_TYPE\nDEFAULT"}
    ,{"id":"10245225236233613.10245225236816887", "label":"e4__t3__MDS_LOOKUP_REPLY_TYPE\nMDSCLIENTCACHE_HIT"}
    ,{"id":"10245225236233613.10245225236827260", "label":"e4__t3__SSIO_START_TYPE\nSSIO_WRITE_START"}
    ,{"id":"10245225236233613.10245225236838847", "label":"e4__t3__ENCODE_START_TYPE\nDEFAULT"}
    ,{"id":"10245225236233613.10245225236892270", "label":"e4__t3__ENCODE_END_TYPE\nDEFAULT"}
    ,{"id":"10245225235856505.10245225235982453", "label":"e10__t3__RPC_REPLY_TYPE\nDEFAULT"}
    ,{"id":"10245225235856505.10245225235997678", "label":"e10__t3__MDS_CREATE_OBJECT_REPLY_TYPE\nDEFAULT"}
    ,{"id":"10245225235856505.10245225236008298", "label":"e10__t3__MDS_SETATTR_CALL_TYPE\nDEFAULT"}
    ,{"id":"10245225235856505.10245225236225483", "label":"e10__t3__RPC_CALL_TYPE\nDEFAULT"}
    ,{"id":"10245225235762117.10245225235772310", "label":"e4__t3__SSIO_END_TYPE\nSSIO_WRITE_END"}
    ,{"id":"10245225235762117.10245225235838152", "label":"e4__t3__MDS_LOCK_RELEASE_TYPE\nDEFAULT"}
    ,{"id":"10245225235762117.10245225235851975", "label":"e4__t3__RPC_SERVER_REPLY_SENT_TYPE\nDEFAULT"}
    ,{"id":"10245264198984150.10245225235747530", "label":"e4__t3__RPC_REPLY_TYPE\nDEFAULT"}
    ,{"id":"10245225234101138.10245264198912053", "label":"e255__t3__FRONTEND_WRITE_CALL_TYPE\nDEFAULT"}
    ,{"id":"10245225234101138.10245264198930683", "label":"e255__t3__FRONTEND_BLOCK_OP_START_TYPE\nFRONTEND_WRITE"}
    ,{"id":"10245225234101138.10245264198978060", "label":"e255__t3__FRONTEND_WRITE_REPLY_TYPE\nDEFAULT"}
    ,{"id":"10245225234074798.10245225234096473", "label":"e4__t3__RPC_CALL_TYPE\nDEFAULT"}
    ,{"id":"10245225233217285.10245225233357820", "label":"e4__t3__RPC_SERVER_CALL_RECEIVED_TYPE\nDEFAULT"}
    ,{"id":"10245225233217285.10245225233433818", "label":"e4__t3__MDS_LOCK_ACQUIRE_TYPE\nDEFAULT"}
    ,{"id":"10245225233217285.10245225233517600", "label":"e4__t3__MDS_LOCK_DB_ACQUIRE_TYPE\nDEFAULT"}
    ,{"id":"10245225233217285.10245225233555880", "label":"e4__t3__MDS_LOCK_DB_RELEASE_TYPE\nDEFAULT"}
    ,{"id":"10245225233217285.10245225233723055", "label":"e4__t3__MDS_LOCK_ACQUIRE_TYPE\nDEFAULT"}
    ,{"id":"10245225233217285.10245225233797875", "label":"e4__t3__MDS_LOCK_DB_ACQUIRE_TYPE\nDEFAULT"}
    ,{"id":"10245225233217285.10245225233830440", "label":"e4__t3__MDS_LOCK_DB_RELEASE_TYPE\nDEFAULT"}
    ,{"id":"10245225233217285.10245225233935950", "label":"e4__t3__MDS_LOOKUP_CALL_TYPE\nDEFAULT"}
    ,{"id":"10245225233217285.10245225233957903", "label":"e4__t3__MDS_LOCK_ACQUIRE_TYPE\nDEFAULT"}
    ,{"id":"10245225233217285.10245225233982015", "label":"e4__t3__MDS_LOCK_RELEASE_TYPE\nDEFAULT"}
    ,{"id":"10245225233217285.10245225233992290", "label":"e4__t3__MDS_LOOKUP_REPLY_TYPE\nMDSCLIENTCACHE_HIT"}
    ,{"id":"10245225233217285.10245225234003615", "label":"e4__t3__SSIO_START_TYPE\nSSIO_WRITE_START"}
    ,{"id":"10245225233217285.10245225234015255", "label":"e4__t3__ENCODE_START_TYPE\nDEFAULT"}
    ,{"id":"10245225233217285.10245225234065903", "label":"e4__t3__ENCODE_END_TYPE\nDEFAULT"}
    ,{"id":"10245225232761315.10245225232763722", "label":"e10__t3__NFS3_CREATE_CALL_TYPE\nDEFAULT"}
    ,{"id":"10245225232761315.10245225232794870", "label":"e10__t3__NFS_DIRCACHE_CALL_TYPE\nDEFAULT"}
    ,{"id":"10245225232761315.10245225233117865", "label":"e10__t3__NFS_CACHE_BLOCK_OP_TYPE\nNFSCACHE_READ_HIT"}
    ,{"id":"10245225232761315.10245225233148390", "label":"e10__t3__NFS_CACHE_BLOCK_OP_TYPE\nNFSCACHE_READ_HIT"}
    ,{"id":"10245225232761315.10245225233156550", "label":"e10__t3__NFS_DIRCACHE_REPLY_TYPE\nNFSDIRCACHE_ENTRY_NOT_FOUND"}
    ,{"id":"10245225232761315.10245225233186325", "label":"e10__t3__MDS_CREATE_OBJECT_CALL_TYPE\nDEFAULT"}
    ,{"id":"10245225232761315.10245225233210145", "label":"e10__t3__RPC_CALL_TYPE\nDEFAULT"}
  ],
  "edges": [
     {"from":"10245225232761315.10245225232763722", "to":"10245225232761315.10245225232794870", "color":"black","label":"p:1.00\n   a: 10us / 12us\n   s: 2us / 1us"}
    ,{"from":"10245225232761315.10245225232794870", "to":"10245225232761315.10245225233117865", "color":"black","label":"p:1.00\n   a: 104us / 174us\n   s: 6us / 6us"}
    ,{"from":"10245225232761315.10245225233117865", "to":"10245225232761315.10245225233148390", "color":"black","label":"p:1.00\n   a: 11us / 12us\n   s: 2us / 1us"}
    ,{"from":"10245225232761315.10245225233148390", "to":"10245225232761315.10245225233156550", "color":"black","label":"p:1.00\n   a: 5us / 7us\n   s: 2us / 2us"}
    ,{"from":"10245225232761315.10245225233156550", "to":"10245225232761315.10245225233186325", "color":"black","label":"p:1.00\n   a: 11us / 12us\n   s: 1us / 1us"}
    ,{"from":"10245225232761315.10245225233186325", "to":"10245225232761315.10245225233210145", "color":"black","label":"p:1.00\n   a: 9us / 10us\n   s: 0us / 2us"}
    ,{"from":"10245225232761315.10245225233210145", "to":"10245225233217285.10245225233357820", "color":"black","label":"p:1.00\n   a: 53us / 54us\n   s: 3us / 7us"}
    ,{"from":"10245225233217285.10245225233357820", "to":"10245225233217285.10245225233433818", "color":"black","label":"p:1.00\n   a: 41us / 42us\n   s: 12us / 11us"}
    ,{"from":"10245225233217285.10245225233433818", "to":"10245225233217285.10245225233517600", "color":"black","label":"p:1.00\n   a: 29us / 30us\n   s: 3us / 3us"}
    ,{"from":"10245225233217285.10245225233517600", "to":"10245225233217285.10245225233555880", "color":"black","label":"p:1.00\n   a: 11us / 12us\n   s: 1us / 2us"}
    ,{"from":"10245225233217285.10245225233555880", "to":"10245225233217285.10245225233723055", "color":"black","label":"p:1.00\n   a: 56us / 56us\n   s: 1us / 1us"}
    ,{"from":"10245225233217285.10245225233723055", "to":"10245225233217285.10245225233797875", "color":"black","label":"p:1.00\n   a: 29us / 30us\n   s: 3us / 3us"}
    ,{"from":"10245225233217285.10245225233797875", "to":"10245225233217285.10245225233830440", "color":"black","label":"p:1.00\n   a: 11us / 12us\n   s: 1us / 2us"}
    ,{"from":"10245225233217285.10245225233830440", "to":"10245225233217285.10245225233935950", "color":"black","label":"p:1.00\n   a: 39us / 40us\n   s: 4us / 8us"}
    ,{"from":"10245225233217285.10245225233935950", "to":"10245225233217285.10245225233957903", "color":"black","label":"p:1.00\n   a: 7us / 8us\n   s: 0us / 1us"}
    ,{"from":"10245225233217285.10245225233957903", "to":"10245225233217285.10245225233982015", "color":"black","label":"p:1.00\n   a: 8us / 8us\n   s: 2us / 0us"}
    ,{"from":"10245225233217285.10245225233982015", "to":"10245225233217285.10245225233992290", "color":"black","label":"p:1.00\n   a: 4us / 6us\n   s: 1us / 2us"}
    ,{"from":"10245225233217285.10245225233992290", "to":"10245225233217285.10245225234003615", "color":"black","label":"p:1.00\n   a: 4us / 3us\n   s: 1us / 1us"}
    ,{"from":"10245225233217285.10245225234003615", "to":"10245225233217285.10245225234015255", "color":"black","label":"p:1.00\n   a: 4us / 4us\n   s: 0us / 0us"}
    ,{"from":"10245225233217285.10245225234015255", "to":"10245225233217285.10245225234065903", "color":"black","label":"p:1.00\n   a: 19us / 22us\n   s: 3us / 4us"}
    ,{"from":"10245225233217285.10245225234065903", "to":"10245225234074798.10245225234096473", "color":"black","label":"p:1.00\n   a: 10us / 10us\n   s: 1us / 1us"}
    ,{"from":"10245225234074798.10245225234096473", "to":"10245225234101138.10245264198912053", "color":"black","label":"p:0.00\n   a: 0us / 0us\n   s: 0us / 0us"}
    ,{"from":"10245225234101138.10245264198912053", "to":"10245225234101138.10245264198930683", "color":"black","label":"p:1.00\n   a: 6us / 6us\n   s: 0us / 0us"}
    ,{"from":"10245225234101138.10245264198930683", "to":"10245225234101138.10245264198978060", "color":"black","label":"p:1.00\n   a: 15us / 15us\n   s: 2us / 1us"}
    ,{"from":"10245225234101138.10245264198978060", "to":"10245264198984150.10245225235747530", "color":"black","label":"p:0.00\n   a: 0us / 0us\n   s: 0us / 0us"}
    ,{"from":"10245225234074798.10245225234096473", "to":"10245264198984150.10245225235747530", "color":"black","label":"p:0.48\n   a: 514us / 531us\n   s: 32us / 47us"}
    ,{"from":"10245264198984150.10245225235747530", "to":"10245225235762117.10245225235772310", "color":"black","label":"p:1.00\n   a: 8us / 9us\n   s: 1us / 1us"}
    ,{"from":"10245225235762117.10245225235772310", "to":"10245225235762117.10245225235838152", "color":"black","label":"p:1.00\n   a: 21us / 22us\n   s: 1us / 2us"}
    ,{"from":"10245225235762117.10245225235838152", "to":"10245225235762117.10245225235851975", "color":"black","label":"p:1.00\n   a: 21us / 21us\n   s: 11us / 12us"}
    ,{"from":"10245225235762117.10245225235851975", "to":"10245225235856505.10245225235982453", "color":"black","label":"p:1.00\n   a: 42us / 43us\n   s: 3us / 2us"}
    ,{"from":"10245225232761315.10245225233210145", "to":"10245225235856505.10245225235982453", "color":"black","label":"p:1.00\n   a: 751us / 772us\n   s: 208us / 223us"}
    ,{"from":"10245225235856505.10245225235982453", "to":"10245225235856505.10245225235997678", "color":"black","label":"p:1.00\n   a: 5us / 5us\n   s: 0us / 0us"}
    ,{"from":"10245225235856505.10245225235997678", "to":"10245225235856505.10245225236008298", "color":"black","label":"p:1.00\n   a: 4us / 3us\n   s: 0us / 0us"}
    ,{"from":"10245225235856505.10245225236008298", "to":"10245225235856505.10245225236225483", "color":"black","label":"p:1.00\n   a: 74us / 74us\n   s: 3us / 1us"}
    ,{"from":"10245225235856505.10245225236225483", "to":"10245225236233613.10245225236391982", "color":"black","label":"p:1.00\n   a: 53us / 54us\n   s: 3us / 7us"}
    ,{"from":"10245225236233613.10245225236391982", "to":"10245225236233613.10245225236536635", "color":"black","label":"p:1.00\n   a: 41us / 42us\n   s: 12us / 11us"}
    ,{"from":"10245225236233613.10245225236536635", "to":"10245225236233613.10245225236624317", "color":"black","label":"p:1.00\n   a: 29us / 30us\n   s: 3us / 3us"}
    ,{"from":"10245225236233613.10245225236624317", "to":"10245225236233613.10245225236653800", "color":"black","label":"p:1.00\n   a: 11us / 12us\n   s: 1us / 2us"}
    ,{"from":"10245225236233613.10245225236653800", "to":"10245225236233613.10245225236762220", "color":"black","label":"p:1.00\n   a: 39us / 40us\n   s: 4us / 8us"}
    ,{"from":"10245225236233613.10245225236762220", "to":"10245225236233613.10245225236783175", "color":"black","label":"p:1.00\n   a: 7us / 8us\n   s: 0us / 1us"}
    ,{"from":"10245225236233613.10245225236783175", "to":"10245225236233613.10245225236806620", "color":"black","label":"p:1.00\n   a: 8us / 8us\n   s: 2us / 0us"}
    ,{"from":"10245225236233613.10245225236806620", "to":"10245225236233613.10245225236816887", "color":"black","label":"p:1.00\n   a: 4us / 6us\n   s: 1us / 2us"}
    ,{"from":"10245225236233613.10245225236816887", "to":"10245225236233613.10245225236827260", "color":"black","label":"p:1.00\n   a: 4us / 3us\n   s: 1us / 1us"}
    ,{"from":"10245225236233613.10245225236827260", "to":"10245225236233613.10245225236838847", "color":"black","label":"p:1.00\n   a: 4us / 4us\n   s: 0us / 0us"}
    ,{"from":"10245225236233613.10245225236838847", "to":"10245225236233613.10245225236892270", "color":"black","label":"p:1.00\n   a: 19us / 22us\n   s: 3us / 4us"}
    ,{"from":"10245225236233613.10245225236892270", "to":"10245225236900542.10245225236917822", "color":"black","label":"p:1.00\n   a: 10us / 10us\n   s: 1us / 1us"}
    ,{"from":"10245225236900542.10245225236917822", "to":"10245225236922457.10245264201597240", "color":"black","label":"p:0.00\n   a: 0us / 0us\n   s: 0us / 0us"}
    ,{"from":"10245225236922457.10245264201597240", "to":"10245225236922457.10245264201615758", "color":"black","label":"p:1.00\n   a: 6us / 6us\n   s: 0us / 0us"}
    ,{"from":"10245225236922457.10245264201615758", "to":"10245225236922457.10245264201662093", "color":"black","label":"p:1.00\n   a: 15us / 15us\n   s: 2us / 1us"}
    ,{"from":"10245225236922457.10245264201662093", "to":"10245264201668153.10245225238371360", "color":"black","label":"p:0.00\n   a: 0us / 0us\n   s: 0us / 0us"}
    ,{"from":"10245225236900542.10245225236917822", "to":"10245264201668153.10245225238371360", "color":"black","label":"p:0.48\n   a: 514us / 531us\n   s: 32us / 47us"}
    ,{"from":"10245264201668153.10245225238371360", "to":"10245225238383810.10245225238393230", "color":"black","label":"p:1.00\n   a: 8us / 9us\n   s: 1us / 1us"}
    ,{"from":"10245225238383810.10245225238393230", "to":"10245225238383810.10245225238451880", "color":"black","label":"p:1.00\n   a: 21us / 22us\n   s: 1us / 2us"}
    ,{"from":"10245225238383810.10245225238451880", "to":"10245225238383810.10245225238537950", "color":"black","label":"p:1.00\n   a: 21us / 21us\n   s: 11us / 12us"}
    ,{"from":"10245225238383810.10245225238537950", "to":"10245225238542540.10245225238656953", "color":"black","label":"p:1.00\n   a: 42us / 43us\n   s: 3us / 2us"}
    ,{"from":"10245225235856505.10245225236225483", "to":"10245225238542540.10245225238656953", "color":"black","label":"p:1.00\n   a: 751us / 772us\n   s: 208us / 223us"}
    ,{"from":"10245225238542540.10245225238656953", "to":"10245225238542540.10245225238706565", "color":"black","label":"p:1.00\n   a: 13us / 13us\n   s: 4us / 3us"}
    ,{"from":"10245225238542540.10245225238706565", "to":"10245225238542540.10245225238900538", "color":"black","label":"p:1.00\n   a: 66us / 68us\n   s: 4us / 4us"}
    ,{"from":"10245225238542540.10245225238900538", "to":"10245225238542540.10245225238920705", "color":"black","label":"p:1.00\n   a: 7us / 7us\n   s: 0us / 1us"}
    ,{"from":"10245225238542540.10245225238920705", "to":"10245225238542540.10245225238942913", "color":"black","label":"p:1.00\n   a: 8us / 10us\n   s: 1us / 1us"}
    ,{"from":"10245225238542540.10245225238942913", "to":"10245225238542540.10245225238956053", "color":"black","label":"p:1.00\n   a: 4us / 4us\n   s: 0us / 0us"}
    ,{"from":"10245225238542540.10245225238956053", "to":"10245225238542540.10245225238976183", "color":"black","label":"p:1.00\n   a: 6us / 7us\n   s: 0us / 2us"}
    ,{"from":"10245225238542540.10245225238976183", "to":"10245225238542540.10245225239036985", "color":"black","label":"p:1.00\n   a: 14us / 15us\n   s: 2us / 2us"}
    ,{"from":"10245225238542540.10245225239036985", "to":"10245225239050590.10245225239072790", "color":"black","label":"p:1.00\n   a: 12us / 12us\n   s: 1us / 2us"}
    ,{"from":"10245225239050590.10245225239072790", "to":"10245225239077703.10245212653147680", "color":"black","label":"p:0.00\n   a: 0us / 0us\n   s: 0us / 0us"}
    ,{"from":"10245225239077703.10245212653147680", "to":"10245225239077703.10245212653168125", "color":"black","label":"p:1.00\n   a: 7us / 7us\n   s: 0us / 0us"}
    ,{"from":"10245225239077703.10245212653168125", "to":"10245225239077703.10245212653266368", "color":"black","label":"p:1.00\n   a: 28us / 28us\n   s: 2us / 2us"}
    ,{"from":"10245225239077703.10245212653266368", "to":"10245212653272938.10245225240261405", "color":"black","label":"p:0.00\n   a: 0us / 0us\n   s: 0us / 0us"}
    ,{"from":"10245225239050590.10245225239072790", "to":"10245212653272938.10245225240261405", "color":"black","label":"p:1.00\n   a: 751us / 772us\n   s: 208us / 223us"}
    ,{"from":"10245212653272938.10245225240261405", "to":"10245225240279840.10245225240292867", "color":"black","label":"p:1.00\n   a: 10us / 10us\n   s: 0us / 1us"}
    ,{"from":"10245225240279840.10245225240292867", "to":"10245225240279840.10245225240316215", "color":"black","label":"p:1.00\n   a: 8us / 7us\n   s: 0us / 0us"}
    ,{"from":"10245225240279840.10245225240316215", "to":"10245225240279840.10245225240534165", "color":"black","label":"p:1.00\n   a: 74us / 74us\n   s: 3us / 1us"}
    ,{"from":"10245225240279840.10245225240534165", "to":"10245225240539850.10245225240695820", "color":"black","label":"p:1.00\n   a: 53us / 54us\n   s: 3us / 7us"}
    ,{"from":"10245225240539850.10245225240695820", "to":"10245225240539850.10245225240847350", "color":"black","label":"p:1.00\n   a: 41us / 42us\n   s: 12us / 11us"}
    ,{"from":"10245225240539850.10245225240847350", "to":"10245225240539850.10245225240942720", "color":"black","label":"p:1.00\n   a: 29us / 30us\n   s: 3us / 3us"}
    ,{"from":"10245225240539850.10245225240942720", "to":"10245225240539850.10245225240977468", "color":"black","label":"p:1.00\n   a: 11us / 12us\n   s: 1us / 2us"}
    ,{"from":"10245225240539850.10245225240977468", "to":"10245225240539850.10245225241114020", "color":"black","label":"p:1.00\n   a: 39us / 40us\n   s: 4us / 8us"}
    ,{"from":"10245225240539850.10245225241114020", "to":"10245225240539850.10245225241136663", "color":"black","label":"p:1.00\n   a: 7us / 8us\n   s: 0us / 1us"}
    ,{"from":"10245225240539850.10245225241136663", "to":"10245225240539850.10245225241162703", "color":"black","label":"p:1.00\n   a: 8us / 8us\n   s: 2us / 0us"}
    ,{"from":"10245225240539850.10245225241162703", "to":"10245225240539850.10245225241174020", "color":"black","label":"p:1.00\n   a: 4us / 6us\n   s: 1us / 2us"}
    ,{"from":"10245225240539850.10245225241174020", "to":"10245225240539850.10245225241183358", "color":"black","label":"p:1.00\n   a: 4us / 3us\n   s: 1us / 1us"}
    ,{"from":"10245225240539850.10245225241183358", "to":"10245225240539850.10245225241197008", "color":"black","label":"p:1.00\n   a: 4us / 4us\n   s: 0us / 0us"}
    ,{"from":"10245225240539850.10245225241197008", "to":"10245225240539850.10245225241270155", "color":"black","label":"p:1.00\n   a: 19us / 22us\n   s: 3us / 4us"}
    ,{"from":"10245225240539850.10245225241270155", "to":"10245225241279140.10245225241301768", "color":"black","label":"p:1.00\n   a: 10us / 10us\n   s: 1us / 1us"}
    ,{"from":"10245225241279140.10245225241301768", "to":"10245225241306425.10245264206055510", "color":"black","label":"p:0.00\n   a: 0us / 0us\n   s: 0us / 0us"}
    ,{"from":"10245225241306425.10245264206055510", "to":"10245225241306425.10245264206073773", "color":"black","label":"p:1.00\n   a: 6us / 6us\n   s: 0us / 0us"}
    ,{"from":"10245225241306425.10245264206073773", "to":"10245225241306425.10245264206120310", "color":"black","label":"p:1.00\n   a: 15us / 15us\n   s: 2us / 1us"}
    ,{"from":"10245225241306425.10245264206120310", "to":"10245264206126378.10245225242876775", "color":"black","label":"p:0.00\n   a: 0us / 0us\n   s: 0us / 0us"}
    ,{"from":"10245225241279140.10245225241301768", "to":"10245264206126378.10245225242876775", "color":"black","label":"p:0.48\n   a: 514us / 531us\n   s: 32us / 47us"}
    ,{"from":"10245264206126378.10245225242876775", "to":"10245225242891722.10245225242903265", "color":"black","label":"p:1.00\n   a: 8us / 9us\n   s: 1us / 1us"}
    ,{"from":"10245225242891722.10245225242903265", "to":"10245225242891722.10245225242964885", "color":"black","label":"p:1.00\n   a: 21us / 22us\n   s: 1us / 2us"}
    ,{"from":"10245225242891722.10245225242964885", "to":"10245225242891722.10245225243051225", "color":"black","label":"p:1.00\n   a: 21us / 21us\n   s: 11us / 12us"}
    ,{"from":"10245225242891722.10245225243051225", "to":"10245225243073327.10245225243205178", "color":"black","label":"p:1.00\n   a: 42us / 43us\n   s: 3us / 2us"}
    ,{"from":"10245225240279840.10245225240534165", "to":"10245225243073327.10245225243205178", "color":"black","label":"p:1.00\n   a: 751us / 772us\n   s: 208us / 223us"}
    ,{"from":"10245225243073327.10245225243205178", "to":"10245225243073327.10245225243233243", "color":"black","label":"p:1.00\n   a: 13us / 13us\n   s: 4us / 3us"}
    ,{"from":"10245225243073327.10245225243233243", "to":"10245225243073327.10245225243265388", "color":"black","label":"p:1.00\n   a: 10us / 11us\n   s: 1us / 2us"}
    ]
}
